{
  "generated_at": "2026-07-08 06:24:04 UTC+08:00",
  "candidates": [
    {
      "id": "reference-sysi-nccu-edu-tw-7a61ac9d",
      "title": "2026 永續發展與企業社會責任(ESG)學術研討會",
      "organizer": "政治大學商學院信義書院",
      "homepage_url": "https://sysi.nccu.edu.tw/",
      "submission_url": "https://sysi.nccu.edu.tw/",
      "registration_url": "",
      "event_start": "2026-09-25",
      "event_end": "2026-09-25",
      "location": "台北市 (政治大學商學院)",
      "submission_deadline": "2026-09-20",
      "submission_fee": "",
      "registration_fee": "",
      "publication_opportunities": [],
      "fields": [
        "免費",
        "混合(線上+實體)",
        "永續ESG"
      ],
      "presentation_formats": [
        "other"
      ],
      "presentation_languages": [
        "unknown"
      ],
      "attention_notes": [
        "由外部研討會資訊站「國立虎尾科技大學財務金融系商管研討會資訊網」每日比對發現，須回到主辦單位官方頁確認日期、投稿與發表形式。"
      ],
      "last_checked": "2026-07-08",
      "last_changed": "2026-06-05",
      "change_status": "new",
      "change_label": "候選新增",
      "change_summary": "每日來源掃描發現的新候選項目。",
      "review_status": "candidate",
      "evidence_sources": [
        {
          "name": "國立虎尾科技大學財務金融系商管研討會資訊網",
          "url": "https://twconference-1010569583715.asia-east1.run.app",
          "type": "reference"
        }
      ],
      "evidence_source_count": 1,
      "independent_source_count": 1,
      "is_corroborated": false,
      "first_seen": "2026-06-05",
      "last_seen": "2026-07-08",
      "candidate_status": "pending",
      "review_notes": "",
      "is_stale": false,
      "information_quality": {
        "score": 2,
        "max_score": 5,
        "label": "部分完整",
        "criteria": [
          "日期與地點完整",
          "投稿方式完整"
        ]
      }
    },
    {
      "id": "reference-www-tims-org-tw-c13387c5",
      "title": "2026 行銷科學學術研討會暨年會",
      "organizer": "台灣行銷科學學會、臺灣大學工商管理學系",
      "homepage_url": "http://www.tims.org.tw/news_detail.php?id=324",
      "submission_url": "http://www.tims.org.tw/news_detail.php?id=324",
      "registration_url": "",
      "event_start": "2026-11-14",
      "event_end": "2026-11-14",
      "location": "台北市 (臺灣大學管理學院二號館)",
      "submission_deadline": "2026-11-05",
      "submission_fee": "",
      "registration_fee": "",
      "publication_opportunities": [],
      "fields": [
        "付費",
        "實體活動",
        "行銷科學"
      ],
      "presentation_formats": [
        "other"
      ],
      "presentation_languages": [
        "unknown"
      ],
      "attention_notes": [
        "由外部研討會資訊站「國立虎尾科技大學財務金融系商管研討會資訊網」每日比對發現，須回到主辦單位官方頁確認日期、投稿與發表形式。"
      ],
      "last_checked": "2026-07-08",
      "last_changed": "2026-06-05",
      "change_status": "new",
      "change_label": "候選新增",
      "change_summary": "每日來源掃描發現的新候選項目。",
      "review_status": "candidate",
      "evidence_sources": [
        {
          "name": "國立虎尾科技大學財務金融系商管研討會資訊網",
          "url": "https://twconference-1010569583715.asia-east1.run.app",
          "type": "reference"
        }
      ],
      "evidence_source_count": 1,
      "independent_source_count": 1,
      "is_corroborated": false,
      "first_seen": "2026-06-05",
      "last_seen": "2026-07-08",
      "candidate_status": "pending",
      "review_notes": "",
      "is_stale": false,
      "information_quality": {
        "score": 2,
        "max_score": 5,
        "label": "部分完整",
        "criteria": [
          "日期與地點完整",
          "投稿方式完整"
        ]
      }
    },
    {
      "id": "reference-business-stust-edu-tw-13a51a40",
      "title": "南臺科技大學「2026第二十二屆知識經濟與全球化管理國際研討會」",
      "organizer": "南臺科技大學",
      "homepage_url": "https://business.stust.edu.tw/tc/node/conference",
      "submission_url": "https://business.stust.edu.tw/tc/node/conference",
      "registration_url": "",
      "event_start": "2026-10-15",
      "event_end": "2026-10-15",
      "location": "南臺科技大學",
      "submission_deadline": "",
      "submission_fee": "",
      "registration_fee": "",
      "publication_opportunities": [],
      "fields": [
        "商管",
        "學術消息"
      ],
      "presentation_formats": [
        "other"
      ],
      "presentation_languages": [
        "unknown"
      ],
      "attention_notes": [
        "由外部研討會資訊站「國立虎尾科技大學財務金融系商管研討會資訊網」每日比對發現，須回到主辦單位官方頁確認日期、投稿與發表形式。"
      ],
      "last_checked": "2026-07-08",
      "last_changed": "2026-06-07",
      "change_status": "new",
      "change_label": "候選新增",
      "change_summary": "每日來源掃描發現的新候選項目。",
      "review_status": "candidate",
      "evidence_sources": [
        {
          "name": "國立虎尾科技大學財務金融系商管研討會資訊網",
          "url": "https://twconference-1010569583715.asia-east1.run.app",
          "type": "reference"
        }
      ],
      "evidence_source_count": 1,
      "independent_source_count": 1,
      "is_corroborated": false,
      "first_seen": "2026-06-07",
      "last_seen": "2026-07-08",
      "candidate_status": "pending",
      "review_notes": "",
      "is_stale": false,
      "information_quality": {
        "score": 1,
        "max_score": 5,
        "label": "資料有限",
        "criteria": [
          "日期與地點完整"
        ]
      }
    },
    {
      "id": "reference-dept-sju-edu-tw-700baccc",
      "title": "聖約翰科技大學「2026智慧、樂活與商業全國性研討會」",
      "organizer": "聖約翰科技大學",
      "homepage_url": "https://dept.sju.edu.tw/download.html?d_no=44&u_id=44",
      "submission_url": "https://dept.sju.edu.tw/download.html?d_no=44&u_id=44",
      "registration_url": "",
      "event_start": "2026-10-15",
      "event_end": "2026-10-15",
      "location": "聖約翰科技大學",
      "submission_deadline": "",
      "submission_fee": "",
      "registration_fee": "",
      "publication_opportunities": [],
      "fields": [
        "商管",
        "學術消息"
      ],
      "presentation_formats": [
        "other"
      ],
      "presentation_languages": [
        "unknown"
      ],
      "attention_notes": [
        "由外部研討會資訊站「國立虎尾科技大學財務金融系商管研討會資訊網」每日比對發現，須回到主辦單位官方頁確認日期、投稿與發表形式。"
      ],
      "last_checked": "2026-07-08",
      "last_changed": "2026-06-07",
      "change_status": "new",
      "change_label": "候選新增",
      "change_summary": "每日來源掃描發現的新候選項目。",
      "review_status": "candidate",
      "evidence_sources": [
        {
          "name": "國立虎尾科技大學財務金融系商管研討會資訊網",
          "url": "https://twconference-1010569583715.asia-east1.run.app",
          "type": "reference"
        }
      ],
      "evidence_source_count": 1,
      "independent_source_count": 1,
      "is_corroborated": false,
      "first_seen": "2026-06-07",
      "last_seen": "2026-07-08",
      "candidate_status": "pending",
      "review_notes": "",
      "is_stale": false,
      "information_quality": {
        "score": 1,
        "max_score": 5,
        "label": "資料有限",
        "criteria": [
          "日期與地點完整"
        ]
      }
    },
    {
      "id": "reference-ihp-knu-edu-tw-849b6411",
      "title": "開南大學「2026國際企業經營管理暨智慧永續發展研討會」",
      "organizer": "開南大學",
      "homepage_url": "http://ihp.knu.edu.tw/",
      "submission_url": "http://ihp.knu.edu.tw/",
      "registration_url": "",
      "event_start": "2026-10-15",
      "event_end": "2026-10-15",
      "location": "開南大學",
      "submission_deadline": "",
      "submission_fee": "",
      "registration_fee": "",
      "publication_opportunities": [],
      "fields": [
        "商管",
        "學術消息"
      ],
      "presentation_formats": [
        "other"
      ],
      "presentation_languages": [
        "unknown"
      ],
      "attention_notes": [
        "由外部研討會資訊站「國立虎尾科技大學財務金融系商管研討會資訊網」每日比對發現，須回到主辦單位官方頁確認日期、投稿與發表形式。"
      ],
      "last_checked": "2026-07-08",
      "last_changed": "2026-06-07",
      "change_status": "new",
      "change_label": "候選新增",
      "change_summary": "每日來源掃描發現的新候選項目。",
      "review_status": "candidate",
      "evidence_sources": [
        {
          "name": "國立虎尾科技大學財務金融系商管研討會資訊網",
          "url": "https://twconference-1010569583715.asia-east1.run.app",
          "type": "reference"
        }
      ],
      "evidence_source_count": 1,
      "independent_source_count": 1,
      "is_corroborated": false,
      "first_seen": "2026-06-07",
      "last_seen": "2026-07-08",
      "candidate_status": "pending",
      "review_notes": "",
      "is_stale": false,
      "information_quality": {
        "score": 1,
        "max_score": 5,
        "label": "資料有限",
        "criteria": [
          "日期與地點完整"
        ]
      }
    },
    {
      "id": "reference-ncwia-org-tw-cbc19c47",
      "title": "雲林科技大學「第十六屆網路智能與應用研討會(NCWIA2026)」",
      "organizer": "雲林科技大學",
      "homepage_url": "https://ncwia.org.tw",
      "submission_url": "https://ncwia.org.tw",
      "registration_url": "",
      "event_start": "2026-10-15",
      "event_end": "2026-10-15",
      "location": "雲林科技大學",
      "submission_deadline": "",
      "submission_fee": "",
      "registration_fee": "",
      "publication_opportunities": [],
      "fields": [
        "商管",
        "學術消息"
      ],
      "presentation_formats": [
        "other"
      ],
      "presentation_languages": [
        "unknown"
      ],
      "attention_notes": [
        "由外部研討會資訊站「國立虎尾科技大學財務金融系商管研討會資訊網」每日比對發現，須回到主辦單位官方頁確認日期、投稿與發表形式。"
      ],
      "last_checked": "2026-07-08",
      "last_changed": "2026-06-07",
      "change_status": "new",
      "change_label": "候選新增",
      "change_summary": "每日來源掃描發現的新候選項目。",
      "review_status": "candidate",
      "evidence_sources": [
        {
          "name": "國立虎尾科技大學財務金融系商管研討會資訊網",
          "url": "https://twconference-1010569583715.asia-east1.run.app",
          "type": "reference"
        }
      ],
      "evidence_source_count": 1,
      "independent_source_count": 1,
      "is_corroborated": false,
      "first_seen": "2026-06-07",
      "last_seen": "2026-07-08",
      "candidate_status": "pending",
      "review_notes": "",
      "is_stale": false,
      "information_quality": {
        "score": 1,
        "max_score": 5,
        "label": "資料有限",
        "criteria": [
          "日期與地點完整"
        ]
      }
    },
    {
      "id": "reference-sfic-fju-edu-tw-27d756e1",
      "title": "輔仁大學「2026國際永續大師高峰論壇學術研討會」",
      "organizer": "輔仁大學",
      "homepage_url": "https://sfic.fju.edu.tw/",
      "submission_url": "https://sfic.fju.edu.tw/",
      "registration_url": "",
      "event_start": "2026-10-15",
      "event_end": "2026-10-15",
      "location": "輔仁大學",
      "submission_deadline": "",
      "submission_fee": "",
      "registration_fee": "",
      "publication_opportunities": [],
      "fields": [
        "商管",
        "學術消息"
      ],
      "presentation_formats": [
        "other"
      ],
      "presentation_languages": [
        "unknown"
      ],
      "attention_notes": [
        "由外部研討會資訊站「國立虎尾科技大學財務金融系商管研討會資訊網」每日比對發現，須回到主辦單位官方頁確認日期、投稿與發表形式。"
      ],
      "last_checked": "2026-07-08",
      "last_changed": "2026-06-07",
      "change_status": "new",
      "change_label": "候選新增",
      "change_summary": "每日來源掃描發現的新候選項目。",
      "review_status": "candidate",
      "evidence_sources": [
        {
          "name": "國立虎尾科技大學財務金融系商管研討會資訊網",
          "url": "https://twconference-1010569583715.asia-east1.run.app",
          "type": "reference"
        }
      ],
      "evidence_source_count": 1,
      "independent_source_count": 1,
      "is_corroborated": false,
      "first_seen": "2026-06-07",
      "last_seen": "2026-07-08",
      "candidate_status": "pending",
      "review_notes": "",
      "is_stale": false,
      "information_quality": {
        "score": 1,
        "max_score": 5,
        "label": "資料有限",
        "criteria": [
          "日期與地點完整"
        ]
      }
    },
    {
      "id": "reference-www-cimi-org-tw-0465fdde",
      "title": "朝陽科技大學「2026第15屆中華創新管理學會學術暨實務研討會」",
      "organizer": "朝陽科技大學",
      "homepage_url": "https://www.cimi.org.tw/newsdetail.php?id=59",
      "submission_url": "https://www.cimi.org.tw/newsdetail.php?id=59",
      "registration_url": "",
      "event_start": "2026-10-15",
      "event_end": "2026-10-15",
      "location": "朝陽科技大學",
      "submission_deadline": "",
      "submission_fee": "",
      "registration_fee": "",
      "publication_opportunities": [],
      "fields": [
        "商管",
        "學術消息"
      ],
      "presentation_formats": [
        "other"
      ],
      "presentation_languages": [
        "unknown"
      ],
      "attention_notes": [
        "由外部研討會資訊站「國立虎尾科技大學財務金融系商管研討會資訊網」每日比對發現，須回到主辦單位官方頁確認日期、投稿與發表形式。"
      ],
      "last_checked": "2026-07-08",
      "last_changed": "2026-06-07",
      "change_status": "new",
      "change_label": "候選新增",
      "change_summary": "每日來源掃描發現的新候選項目。",
      "review_status": "candidate",
      "evidence_sources": [
        {
          "name": "國立虎尾科技大學財務金融系商管研討會資訊網",
          "url": "https://twconference-1010569583715.asia-east1.run.app",
          "type": "reference"
        }
      ],
      "evidence_source_count": 1,
      "independent_source_count": 1,
      "is_corroborated": false,
      "first_seen": "2026-06-07",
      "last_seen": "2026-07-08",
      "candidate_status": "pending",
      "review_notes": "",
      "is_stale": false,
      "information_quality": {
        "score": 1,
        "max_score": 5,
        "label": "資料有限",
        "criteria": [
          "日期與地點完整"
        ]
      }
    },
    {
      "id": "organizer-www-nstc-gov-tw-e882c3b9",
      "title": "【研討會報名】The 4th International Symposium on Agricultural Net-Zero Carbon Technology and Management Innovation: Circular Bioeconomy System（115年7月24日、集思台大會議中心）",
      "organizer": "國家科學及技術委員會活動訊息（第 1 頁）",
      "homepage_url": "https://www.nstc.gov.tw/folksonomy/detail/f7ac0e66-1607-423f-b984-e473829b26bc?l=ch",
      "submission_url": "https://www.nstc.gov.tw/folksonomy/detail/f7ac0e66-1607-423f-b984-e473829b26bc?l=ch",
      "registration_url": "",
      "event_start": "2026-07-24",
      "event_end": "2026-07-24",
      "location": "待確認",
      "submission_deadline": "",
      "submission_fee": "",
      "registration_fee": "",
      "publication_opportunities": [],
      "fields": [
        "待確認"
      ],
      "presentation_formats": [
        "other"
      ],
      "presentation_languages": [
        "unknown"
      ],
      "attention_notes": [
        "由「國家科學及技術委員會活動訊息（第 1 頁）」官方網站每日掃描發現，已通過正式研討會初步篩選，仍待人工確認日期、投稿與發表形式。"
      ],
      "last_checked": "2026-07-08",
      "last_changed": "2026-06-29",
      "change_status": "new",
      "change_label": "候選新增",
      "change_summary": "每日來源掃描發現的新候選項目。",
      "review_status": "candidate",
      "discovered_from_url": "https://www.nstc.gov.tw/folksonomy/list/e25373b0-6a33-4a48-ae74-85cae48f1b72?l=ch",
      "evidence_sources": [
        {
          "name": "國家科學及技術委員會活動訊息（第 1 頁）",
          "url": "https://www.nstc.gov.tw/folksonomy/list/e25373b0-6a33-4a48-ae74-85cae48f1b72?l=ch",
          "type": "government"
        }
      ],
      "evidence_source_count": 1,
      "independent_source_count": 1,
      "is_corroborated": false,
      "first_seen": "2026-06-08",
      "last_seen": "2026-07-08",
      "candidate_status": "pending",
      "review_notes": "",
      "is_stale": false,
      "information_quality": {
        "score": 0,
        "max_score": 5,
        "label": "資料不足",
        "criteria": []
      }
    },
    {
      "id": "reference-www-finance-org-tw-295a0e74",
      "title": "2026 Three Asian Countries Finance Conference(2026/9/4)",
      "organizer": "臺灣財務金融學會",
      "homepage_url": "https://www.finance.org.tw/fnmeeting_item/70",
      "submission_url": "https://www.finance.org.tw/fnmeeting_item/70",
      "registration_url": "",
      "event_start": "2026-09-04",
      "event_end": "2026-09-04",
      "location": "會議地點：國立政治大學商學院6樓義育廳",
      "submission_deadline": "",
      "submission_fee": "",
      "registration_fee": "",
      "publication_opportunities": [],
      "fields": [
        "財務金融",
        "專題研討會",
        "學術消息"
      ],
      "presentation_formats": [
        "other"
      ],
      "presentation_languages": [
        "unknown"
      ],
      "attention_notes": [
        "由外部研討會資訊站「國立虎尾科技大學財務金融系商管研討會資訊網」每日比對發現，須回到主辦單位官方頁確認日期、投稿與發表形式。"
      ],
      "last_checked": "2026-06-20",
      "last_changed": "2026-06-19",
      "change_status": "new",
      "change_label": "候選新增",
      "change_summary": "每日來源掃描發現的新候選項目。",
      "review_status": "candidate",
      "evidence_sources": [
        {
          "name": "國立虎尾科技大學財務金融系商管研討會資訊網",
          "url": "https://twconference-1010569583715.asia-east1.run.app",
          "type": "reference"
        }
      ],
      "evidence_source_count": 1,
      "independent_source_count": 1,
      "is_corroborated": false,
      "first_seen": "2026-06-18",
      "last_seen": "2026-06-20",
      "candidate_status": "pending",
      "review_notes": "",
      "is_stale": true,
      "information_quality": {
        "score": 1,
        "max_score": 5,
        "label": "資料有限",
        "criteria": [
          "日期與地點完整"
        ]
      }
    },
    {
      "id": "organizer-review-management-ntu-edu-tw-30100b9b",
      "title": "2026海峽兩岸經濟管理理論與實務研討會，歡迎各界踴躍投稿第一波至5/30第二波至6/15（會議地點：深圳）",
      "organizer": "臺大管理論叢",
      "homepage_url": "https://review.management.ntu.edu.tw/news.aspx?lang=cht&pid=340",
      "submission_url": "https://review.management.ntu.edu.tw/news.aspx?lang=cht&pid=340",
      "registration_url": "",
      "event_start": "",
      "event_end": "",
      "location": "待確認",
      "submission_deadline": "",
      "submission_fee": "",
      "registration_fee": "",
      "publication_opportunities": [],
      "fields": [
        "待確認"
      ],
      "presentation_formats": [
        "other"
      ],
      "presentation_languages": [
        "unknown"
      ],
      "attention_notes": [
        "由「臺大管理論叢」官方網站每日掃描發現，已通過正式研討會初步篩選，仍待人工確認日期、投稿與發表形式。"
      ],
      "last_checked": "2026-06-20",
      "last_changed": "2026-06-20",
      "change_status": "new",
      "change_label": "候選新增",
      "change_summary": "每日來源掃描發現的新候選項目。",
      "review_status": "candidate",
      "discovered_from_url": "https://review.management.ntu.edu.tw/",
      "evidence_sources": [
        {
          "name": "臺大管理論叢",
          "url": "https://review.management.ntu.edu.tw/",
          "type": "scholarly"
        }
      ],
      "evidence_source_count": 1,
      "independent_source_count": 1,
      "is_corroborated": false,
      "first_seen": "2026-06-20",
      "last_seen": "2026-06-20",
      "candidate_status": "pending",
      "review_notes": "",
      "is_stale": true,
      "information_quality": {
        "score": 0,
        "max_score": 5,
        "label": "資料不足",
        "criteria": []
      }
    },
    {
      "id": "organizer-review-management-ntu-edu-tw-cbb8e182",
      "title": "2027 Management Theory and Practice Conference | April 5 – 6, 2027 | Kyoto University, Japan．Submission Deadline: April ",
      "organizer": "臺大管理論叢",
      "homepage_url": "https://review.management.ntu.edu.tw/news.aspx?lang=cht&pid=341",
      "submission_url": "https://review.management.ntu.edu.tw/news.aspx?lang=cht&pid=341",
      "registration_url": "",
      "event_start": "",
      "event_end": "",
      "location": "待確認",
      "submission_deadline": "",
      "submission_fee": "",
      "registration_fee": "",
      "publication_opportunities": [],
      "fields": [
        "待確認"
      ],
      "presentation_formats": [
        "other"
      ],
      "presentation_languages": [
        "unknown"
      ],
      "attention_notes": [
        "由「臺大管理論叢」官方網站每日掃描發現，已通過正式研討會初步篩選，仍待人工確認日期、投稿與發表形式。"
      ],
      "last_checked": "2026-06-20",
      "last_changed": "2026-06-20",
      "change_status": "new",
      "change_label": "候選新增",
      "change_summary": "每日來源掃描發現的新候選項目。",
      "review_status": "candidate",
      "discovered_from_url": "https://review.management.ntu.edu.tw/",
      "evidence_sources": [
        {
          "name": "臺大管理論叢",
          "url": "https://review.management.ntu.edu.tw/",
          "type": "scholarly"
        }
      ],
      "evidence_source_count": 1,
      "independent_source_count": 1,
      "is_corroborated": false,
      "first_seen": "2026-06-20",
      "last_seen": "2026-06-20",
      "candidate_status": "pending",
      "review_notes": "",
      "is_stale": true,
      "information_quality": {
        "score": 0,
        "max_score": 5,
        "label": "資料不足",
        "criteria": []
      }
    },
    {
      "id": "organizer-www-finance-org-tw-17e4c6ff",
      "title": "2026 Three Asian Countries Finance Conference(2026/9/4)",
      "organizer": "臺灣財務金融學會",
      "homepage_url": "https://www.finance.org.tw/fnnews/51",
      "submission_url": "https://www.finance.org.tw/fnnews/51",
      "registration_url": "",
      "event_start": "2026-09-04",
      "event_end": "2026-09-04",
      "location": "會議地點：國立政治大學商學院6樓義育廳",
      "submission_deadline": "",
      "submission_fee": "",
      "registration_fee": "",
      "publication_opportunities": [],
      "fields": [
        "財務金融",
        "專題研討會",
        "學術消息"
      ],
      "presentation_formats": [
        "other"
      ],
      "presentation_languages": [
        "unknown"
      ],
      "attention_notes": [
        "由常態性研討會或主辦單位官方頁每日掃描發現，已通過正式研討會初步篩選，仍待人工確認日期、投稿與發表形式。",
        "已由 2 個不同網域來源交叉發現；正式資料仍以會議主辦單位公告為準。"
      ],
      "last_checked": "2026-07-08",
      "last_changed": "2026-07-08",
      "change_status": "new",
      "change_label": "候選新增",
      "change_summary": "每日來源掃描發現的新候選項目。",
      "review_status": "candidate",
      "evidence_sources": [
        {
          "name": "臺灣財務金融學會",
          "url": "https://www.finance.org.tw/",
          "type": "organizer"
        },
        {
          "name": "國立虎尾科技大學財務金融系商管研討會資訊網",
          "url": "https://twconference-1010569583715.asia-east1.run.app",
          "type": "reference"
        }
      ],
      "evidence_source_count": 2,
      "independent_source_count": 2,
      "is_corroborated": true,
      "first_seen": "2026-06-20",
      "last_seen": "2026-07-08",
      "candidate_status": "pending",
      "review_notes": "",
      "is_stale": false,
      "information_quality": {
        "score": 1,
        "max_score": 5,
        "label": "資料有限",
        "criteria": [
          "日期與地點完整"
        ]
      }
    },
    {
      "id": "organizer-www-fcu-edu-tw-f509f39f",
      "title": "逢甲大學經濟學系第四屆國際研討會 國內外學者共探永續經濟與綠色金融 逢甲大學經濟學系第四屆國際研討會 國內外學者共探永續經濟與綠色金融",
      "organizer": "逢甲大學商學院",
      "homepage_url": "https://www.fcu.edu.tw/news/2026062601/",
      "submission_url": "https://www.fcu.edu.tw/news/2026062601/",
      "registration_url": "",
      "event_start": "",
      "event_end": "",
      "location": "待確認",
      "submission_deadline": "",
      "submission_fee": "",
      "registration_fee": "",
      "publication_opportunities": [],
      "fields": [
        "待確認"
      ],
      "presentation_formats": [
        "other"
      ],
      "presentation_languages": [
        "unknown"
      ],
      "attention_notes": [
        "由「逢甲大學商學院」官方網站每日掃描發現，已通過正式研討會初步篩選，仍待人工確認日期、投稿與發表形式。"
      ],
      "last_checked": "2026-07-08",
      "last_changed": "2026-07-08",
      "change_status": "new",
      "change_label": "候選新增",
      "change_summary": "每日來源掃描發現的新候選項目。",
      "review_status": "candidate",
      "discovered_from_url": "https://business.fcu.edu.tw/",
      "evidence_sources": [
        {
          "name": "逢甲大學商學院",
          "url": "https://business.fcu.edu.tw/",
          "type": "university_college"
        }
      ],
      "evidence_source_count": 1,
      "independent_source_count": 1,
      "is_corroborated": false,
      "first_seen": "2026-06-27",
      "last_seen": "2026-07-08",
      "candidate_status": "pending",
      "review_notes": "",
      "is_stale": false,
      "information_quality": {
        "score": 0,
        "max_score": 5,
        "label": "資料不足",
        "criteria": []
      }
    }
  ]
}
